jst_playmobile/__init__.py
jst_playmobile/abstract.py
jst_playmobile/client.py
jst_playmobile/entities.py
jst_playmobile/exceptions.py
jst_playmobile/test_utils.py
jst_playmobile-0.1.0.dist-info/METADATA
jst_playmobile-0.1.0.dist-info/WHEEL
jst_playmobile-0.1.0.dist-info/RECORD
