Metadata-Version: 2.1
Name: jst-playmobile
Version: 0.1.0
Summary: 
Author: A'zamov Samandar
Author-email: JscorpTech@gmail.com
Requires-Python: >=3.12,<4.0
Classifier: Programming Language :: Python :: 3
Classifier: Programming Language :: Python :: 3.12
Requires-Dist: attrs (>=24.2.0,<25.0.0)
Requires-Dist: faker (>=29.0.0,<30.0.0)
Requires-Dist: httpx (>=0.27.2,<0.28.0)
Requires-Dist: marshmallow (>=3.22.0,<4.0.0)
